synthneura/__init__.py
synthneura/core/config.py
synthneura/core/logger.py
synthneura/core/schemas.py
synthneura/ingestion/clinical_trials.py
synthneura/services/pipeline.py
synthneura/services/summary.py
synthneura/storage/__init__.py
synthneura/storage/base.py
synthneura/storage/sqlite_sink.py
synthneura/ui/cli.py
synthneura-2.0.0.dist-info/METADATA
synthneura-2.0.0.dist-info/WHEEL
synthneura-2.0.0.dist-info/top_level.txt
synthneura-2.0.0.dist-info/RECORD
