Metadata-Version: 2.4
Name: synthneura
Version: 2.0.0
Requires-Dist: click>=8.1
Requires-Dist: pydantic<3,>=1.10
Requires-Dist: requests>=2.31
Provides-Extra: dev
Requires-Dist: pytest>=7; extra == "dev"
